{
    "title": "OAuth 2.0 Pushed Authorization Requests",
    "link": {
        "@attributes": {
            "href": "/doc/draft-ietf-oauth-par/"
        }
    },
    "id": "819265",
    "updated": "2021-07-29T17:50:30-0700",
    "published": "2021-07-29T17:50:30-0700",
    "author": {
        "name": "Cindy Morgan"
    },
    "content": {
        "@attributes": {
            "type": "html"
        },
        "@text": "IESG has approved the document"
    },
    "ietf": {
        "type": "iesg_approved",
        "stream": "ietf",
        "group": "oauth",
        "shepherd": "Hannes Tschofenig",
        "ad": "Roman Danyliw",
        "state": [
            {
                "@attributes": {
                    "type": "draft"
                },
                "@text": "active"
            },
            {
                "@attributes": {
                    "type": "draft-iana-action"
                },
                "@text": "rfcedack"
            },
            {
                "@attributes": {
                    "type": "draft-iana-experts"
                },
                "@text": "reviewers-ok"
            },
            {
                "@attributes": {
                    "type": "draft-iana-review"
                },
                "@text": "ok-act"
            },
            {
                "@attributes": {
                    "type": "draft-iesg"
                },
                "@text": "rfcqueue"
            },
            {
                "@attributes": {
                    "type": "draft-rfceditor"
                },
                "@text": "edit"
            },
            {
                "@attributes": {
                    "type": "draft-stream-ietf"
                },
                "@text": "sub-pub"
            }
        ]
    }
}